[{"name":"Mais","basicName":"Mais","genericName":"Getreide","saisonVegetables":["Juli","August","September"],"standardIngredient":false,"preparationRequired":false,"amount":1,"unit":"","durability":7,"preparationLongText":""},{"name":"Frühlingszwiebel","basicName":"Frühlingszwiebel","genericName":"Sonstiges Gemüse","saisonVegetables":["Mai","Juni","Juli","August"],"standardIngredient":false,"preparationRequired":false,"amount":1,"unit":"","durability":7,"preparationLongText":""},{"name":"Weizenmehl","basicName":"Weizenmehl","genericName":"Getreide","saisonVegetables":[],"standardIngredient":true,"preparationRequired":false,"amount":50,"unit":"g","durability":180,"preparationLongText":""},{"name":"Gewürzmischung 'Hello Patatas'","basicName":"Gewürzmischung","genericName":"Gewürz","saisonVegetables":[],"standardIngredient":true,"preparationRequired":false,"amount":4,"unit":"g","durability":365,"preparationLongText":""},{"name":"mehligk. Kartoffeln","basicName":"Kartoffel","genericName":"Wurzelgemüse","saisonVegetables":["Juni","Juli","August","September","Oktober"],"standardIngredient":false,"preparationRequired":false,"amount":400,"unit":"g","durability":30,"preparationLongText":""},{"name":"Gurke","basicName":"Gurke","genericName":"Sonstiges Gemüse","saisonVegetables":["Juni","Juli","August","September"],"standardIngredient":false,"preparationRequired":false,"amount":1,"unit":"","durability":7,"preparationLongText":""},{"name":"Tomatenpesto","basicName":"Tomatenpesto","genericName":"Gewürz","saisonVegetables":[],"standardIngredient":false,"preparationRequired":false,"amount":25,"unit":"g","durability":30,"preparationLongText":""},{"name":"Schmand","basicName":"Schmand","genericName":"Milchprodukt","saisonVegetables":[],"standardIngredient":false,"preparationRequired":false,"amount":150,"unit":"g","durability":7,"preparationLongText":""},{"name":"Petersilie glatt","amount":5,"basicName":"Petersilie glatt","unit":"g"},{"name":"Schnittlauch","amount":5,"basicName":"Schnittlauch","unit":"g"},{"name":"Käse-Mix","basicName":"Käse","genericName":"Milchprodukt","saisonVegetables":[],"standardIngredient":false,"preparationRequired":false,"amount":50,"unit":"g","durability":7,"preparationLongText":""},{"name":"Butter","basicName":"Butter","genericName":"Milchprodukt","saisonVegetables":[],"standardIngredient":true,"preparationRequired":false,"amount":10,"unit":"g","durability":30,"preparationLongText":""},{"name":"Zitrone, gewachst","basicName":"Zitrone","genericName":"Obst","saisonVegetables":["Januar","Februar","März","April","Mai","November","Dezember"],"standardIngredient":false,"preparationRequired":false,"amount":1,"unit":"","durability":14,"preparationLongText":""},{"name":"Öl","basicName":"Öl","genericName":"Gewürz","saisonVegetables":[],"standardIngredient":true,"preparationRequired":false,"amount":0,"unit":"","durability":365,"preparationLongText":""},{"name":"Wasser","basicName":"Wasser","genericName":"Getränk","saisonVegetables":[],"standardIngredient":true,"preparationRequired":false,"amount":0,"unit":"","durability":365,"preparationLongText":""},{"name":"Salz","basicName":"Salz","genericName":"Gewürz","saisonVegetables":[],"standardIngredient":true,"preparationRequired":false,"amount":0,"unit":"","durability":365,"preparationLongText":""},{"name":"Pfeffer","basicName":"Pfeffer","genericName":"Gewürz","saisonVegetables":[],"standardIngredient":true,"preparationRequired":false,"amount":0,"unit":"","durability":365,"preparationLongText":""}]