[{"name":"Champignons","basicName":"Champignon","genericName":"Pilz","saisonVegetables":["Januar","Februar","März","April","Mai","Juni","Juli","August","September","Oktober","November","Dezember"],"standardIngredient":false,"preparationRequired":false,"amount":150,"unit":"g","durability":5,"preparationLongText":""},{"name":"Weizenmehl","basicName":"Weizenmehl","genericName":"Getreide","saisonVegetables":[],"standardIngredient":true,"preparationRequired":false,"amount":50,"unit":"g","durability":180,"preparationLongText":""},{"name":"Briochebrötchen","basicName":"Briochebrötchen","genericName":"Getreide","saisonVegetables":[],"standardIngredient":false,"preparationRequired":false,"amount":2,"unit":"","durability":7,"preparationLongText":""},{"name":"Gewürzmischung 'Hello Paprika'","basicName":"Gewürzmischung","genericName":"Gewürz","saisonVegetables":[],"standardIngredient":true,"preparationRequired":false,"amount":4,"unit":"g","durability":365,"preparationLongText":""},{"name":"Worcester Sauce","basicName":"Worcester Sauce","genericName":"Gewürz","saisonVegetables":[],"standardIngredient":true,"preparationRequired":false,"amount":8,"unit":"ml","durability":365,"preparationLongText":""},{"name":"Salatherz (Romana)","basicName":"Salatherz","genericName":"Blattgemüse","saisonVegetables":["Mai","Juni","Juli","August","September"],"standardIngredient":false,"preparationRequired":false,"amount":1,"unit":"","durability":5,"preparationLongText":""},{"name":"Tomate","basicName":"Tomate","genericName":"Sonstiges Gemüse","saisonVegetables":["Juli","August","September","Oktober"],"standardIngredient":false,"preparationRequired":false,"amount":1,"unit":"","durability":5,"preparationLongText":""},{"name":"Mayonnaise","basicName":"Mayonnaise","genericName":"Gewürz","saisonVegetables":[],"standardIngredient":true,"preparationRequired":false,"amount":34,"unit":"ml","durability":30,"preparationLongText":""},{"name":"rote Zwiebel","basicName":"Zwiebel","genericName":"Sonstiges Gemüse","saisonVegetables":["Juli","August","September"],"standardIngredient":true,"preparationRequired":false,"amount":1,"unit":"","durability":30,"preparationLongText":""},{"name":"Balsamico-Crème","basicName":"Balsamico-Crème","genericName":"Gewürz","saisonVegetables":[],"standardIngredient":true,"preparationRequired":false,"amount":12,"unit":"ml","durability":365,"preparationLongText":""},{"name":"Süßkartoffel","basicName":"Süßkartoffel","genericName":"Wurzelgemüse","saisonVegetables":["September","Oktober","November"],"standardIngredient":false,"preparationRequired":false,"amount":1,"unit":"","durability":7,"preparationLongText":""},{"name":"Käse-Mix","basicName":"Käse","genericName":"Milchprodukt","saisonVegetables":[],"standardIngredient":false,"preparationRequired":true,"amount":50,"unit":"g","durability":7,"preparationLongText":"Den Käse reiben"},{"name":"Joghurt","basicName":"Joghurt","genericName":"Milchprodukt","saisonVegetables":[],"standardIngredient":false,"preparationRequired":false,"amount":75,"unit":"g","durability":7,"preparationLongText":""},{"name":"Öl","basicName":"Öl","genericName":"Gewürz","saisonVegetables":[],"standardIngredient":true,"preparationRequired":false,"amount":1,"unit":"EL","durability":365,"preparationLongText":""},{"name":"Wasser","basicName":"Wasser","genericName":"Gewürz","saisonVegetables":[],"standardIngredient":true,"preparationRequired":false,"amount":50,"unit":"ml","durability":365,"preparationLongText":""},{"name":"Salz","basicName":"Salz","genericName":"Gewürz","saisonVegetables":[],"standardIngredient":true,"preparationRequired":false,"amount":0,"unit":"nach Geschmack","durability":365,"preparationLongText":""},{"name":"Pfeffer","basicName":"Pfeffer","genericName":"Gewürz","saisonVegetables":[],"standardIngredient":true,"preparationRequired":false,"amount":0,"unit":"nach Geschmack","durability":365,"preparationLongText":""}]